pdcloud/__init__.py
pdcloud/adapters/__init__.py
pdcloud/adapters/azure.py
pdcloud/core/__init__.py
pdcloud/core/model.py
pdcloud/ports/__init__.py
pdcloud/ports/cloud_storage_port.py
tests/__init__.py
tests/adapters/__init__.py
tests/adapters/test_azure.py
tests/adapters/test_real_azure.py
tests/core/__init__.py
tests/core/test_model.py
pdcloud-0.4.1.dist-info/LICENSE.txt
pdcloud-0.4.1.dist-info/METADATA
pdcloud-0.4.1.dist-info/WHEEL
pdcloud-0.4.1.dist-info/top_level.txt
pdcloud-0.4.1.dist-info/RECORD
