Metadata-Version: 2.1
Name: pdcloud
Version: 0.4.1
Summary: Python pandas dataframe cloud agnostic storage
Home-page: 
Author: Vitali M.
Author-email: pilot@aviatorv.com
License: MIT
Requires-Python: >=3.8
License-File: LICENSE.txt
Requires-Dist: azure-storage-blob
Requires-Dist: pyarrow
Requires-Dist: pandas
Requires-Dist: aiohttp
Requires-Dist: pre-commit <4.0.0,>=2.17.0
Provides-Extra: test
Requires-Dist: pytest ; extra == 'test'
Requires-Dist: pytest-asyncio ; extra == 'test'
Requires-Dist: twine ; extra == 'test'
